Metadata-Version: 2.1
Name: AlphaDSSP
Version: 0.5.1
Summary: Tool for converting Alphafold tar shards to a database of DSSP secondary structure information.
Home-page: https://github.com/noelgarber/AlphaDSSP
Author: Noel Garber
Author-email: ngarber93@gmail.com
Classifier: Programming Language :: Python :: 3
Classifier: Operating System :: OS Independent
License-File: LICENSE
Requires-Dist: numpy
Requires-Dist: tqdm
Requires-Dist: biopython
